edge_research/README.md
edge_research/__init__.py
edge_research/data/README.md
edge_research/data/fundamentals_sample.parquet
edge_research/data/hloc_sample.parquet
edge_research/edge_research_pipeline.egg-info/SOURCES.txt
edge_research/edge_research_pipeline.egg-info/dependency_links.txt
edge_research/edge_research_pipeline.egg-info/entry_points.txt
edge_research/edge_research_pipeline.egg-info/requires.txt
edge_research/edge_research_pipeline.egg-info/top_level.txt
edge_research/logger/README.md
edge_research/logger/__init__.py
edge_research/logger/logger.py
edge_research/logger/.ipynb_checkpoints/README-checkpoint.md
edge_research/params/README.md
edge_research/params/config_schema.py
edge_research/params/config_validator.py
edge_research/params/custom_params.yaml
edge_research/params/default_params.yaml
edge_research/params/grid_params.yaml
edge_research/pipeline/README.md
edge_research/pipeline/__init__.py
edge_research/pipeline/main.py
edge_research/pipeline/pipeline.py
edge_research/pipeline/.ipynb_checkpoints/README-checkpoint.md
edge_research/preprocessing/README.md
edge_research/preprocessing/__init__.py
edge_research/preprocessing/cleaning.py
edge_research/preprocessing/engineering.py
edge_research/preprocessing/target.py
edge_research/preprocessing/.ipynb_checkpoints/README-checkpoint.md
edge_research/rules_mining/README.md
edge_research/rules_mining/__init__.py
edge_research/rules_mining/mining.py
edge_research/rules_mining/.ipynb_checkpoints/README-checkpoint.md
edge_research/statistics/README.md
edge_research/statistics/__init__.py
edge_research/statistics/calculator.py
edge_research/statistics/.ipynb_checkpoints/README-checkpoint.md
edge_research/utils/__init__.py
edge_research/utils/dataset_config.py
edge_research/utils/utils.py
edge_research/validation_tests/__init__.py
edge_research/validation_tests/readme.md
edge_research/validation_tests/validation.py
edge_research/validation_tests/.ipynb_checkpoints/readme-checkpoint.md
edge_research_pipeline-1.1.0.dist-info/licenses/LICENSE
edge_research_pipeline-1.1.0.dist-info/METADATA
edge_research_pipeline-1.1.0.dist-info/WHEEL
edge_research_pipeline-1.1.0.dist-info/entry_points.txt
edge_research_pipeline-1.1.0.dist-info/top_level.txt
edge_research_pipeline-1.1.0.dist-info/RECORD
