Metadata-Version: 2.4
Name: edge-research-pipeline
Version: 1.1.0
Summary: Modular pipeline for quantitative signal discovery and validation
Author-email: Kalle Fischer <contact@khf-research.com>
License: Edge Research Pipeline — Personal Use License (ERPUL)
Project-URL: Homepage, https://github.com/KHFischer/edge-research-pipeline
Project-URL: Documentation, https://github.com/KHFischer/edge-research-pipeline/tree/main/docs
Project-URL: Source, https://github.com/KHFischer/edge-research-pipeline
Project-URL: Issues, https://github.com/KHFischer/edge-research-pipeline/issues
Keywords: rule mining,pattern discovery,interpretable machine learning,feature engineering,tabular data,tabular machine learning,subgroup discovery,signal discovery,data validation,data cleaning pipeline,rule-based modeling,backtesting,bootstrap resampling,walk-forward analysis,synthetic data generation,quantitative research,financial machine learning,quantitative finance,python package
Classifier: Programming Language :: Python :: 3
Classifier: License :: Other/Proprietary License
Classifier: Operating System :: OS Independent
Classifier: Development Status :: 4 - Beta
Classifier: Intended Audience :: Science/Research
Classifier: Topic :: Scientific/Engineering :: Information Analysis
Requires-Python: >=3.8
License-File: LICENSE
Requires-Dist: badgers<0.1,>=0.0.10
Requires-Dist: google_auth<3.0,>=2.40.3
Requires-Dist: imodels<3.0,>=2.0.0
Requires-Dist: joblib<2.0,>=1.4.2
Requires-Dist: mlxtend<0.24,>=0.23.4
Requires-Dist: numpy<2.0,>=1.26.0
Requires-Dist: pandas<2.4,>=2.3.1
Requires-Dist: params<1.0,>=0.9.0
Requires-Dist: pysubgroup<0.9,>=0.8.0
Requires-Dist: PyYAML<7.0,>=6.0.2
Requires-Dist: scikit_eLCS<1.3,>=1.2.4
Requires-Dist: scikit-learn<2.0,>=1.7.1
Requires-Dist: scipy<2.0,>=1.16.1
Requires-Dist: sdv<1.25,>=1.24.1
Requires-Dist: statsmodels<0.15,>=0.14.4
Requires-Dist: tqdm<5.0,>=4.67.1
Provides-Extra: orange
Requires-Dist: orange3<4.0,>=3.39.0; extra == "orange"
Provides-Extra: synth
Requires-Dist: synthcity<0.3,>=0.2.12; extra == "synth"
Dynamic: license-file
